metapy/__init__.py
metapy/evolutionary/__init__.py
metapy/evolutionary/evolutionary.py
metapy/local_search/__init__.py
metapy/local_search/hill_climbing.py
metapy/local_search/ils.py
metapy/tsp/__init__.py
metapy/tsp/bruteforce.py
metapy/tsp/construction.py
metapy/tsp/euclidean.py
metapy/tsp/grasp.py
metapy/tsp/init_solutions.py
metapy/tsp/objective.py
metapy/tsp/tsp_io.py
metapy/tsp/tsp_utility.py
meta_py-0.4.0.dist-info/LICENSE
meta_py-0.4.0.dist-info/METADATA
meta_py-0.4.0.dist-info/WHEEL
meta_py-0.4.0.dist-info/top_level.txt
meta_py-0.4.0.dist-info/RECORD
