Metadata-Version: 2.1
Name: meta-py
Version: 0.4.0
Summary: Metaheuristic and optimisation tools for education
Home-page: https://github.com/TomMonks/meta-py
Author: Thomas Monks
Author-email: t.m.w.monks@exeter.ac.uk
License: The MIT License (MIT)
Platform: UNKNOWN
Classifier: Programming Language :: Python :: 3.7
Classifier: Programming Language :: Python :: 3.8
Classifier: License :: OSI Approved :: MIT License
Classifier: Operating System :: OS Independent
Requires-Python: >=3.7
Requires-Dist: numpy (>=1.19.2)
Requires-Dist: pandas (>=1.1.0)
Requires-Dist: scipy (>=1.5.2)
